journal.py
pyjournal_shrey-0.1.dist-info/METADATA
pyjournal_shrey-0.1.dist-info/WHEEL
pyjournal_shrey-0.1.dist-info/entry_points.txt
pyjournal_shrey-0.1.dist-info/top_level.txt
pyjournal_shrey-0.1.dist-info/RECORD
