Metadata-Version: 2.4
Name: pyjournal-shrey
Version: 0.1
Summary: A simple command-line journal app with search, tagging, and markdown export.
Author: Shrey Mehra
Classifier: Programming Language :: Python :: 3
Classifier: Operating System :: OS Independent
Requires-Python: >=3.6
Dynamic: author
Dynamic: classifier
Dynamic: requires-python
Dynamic: summary
